flask_gordon/__init__.py
flask_gordon/ext/__init__.py
flask_gordon/ext/_functions.py
flask_gordon/ext/ctx.py
flask_gordon/ext/defaults.py
flask_gordon/ext/functions.py
flask_gordon/ext/testing.py
flask_gordon/ext/argparse/__init__.py
flask_gordon/ext/argparse/_functions.py
flask_gordon/ext/argparse/argparse.py
flask_gordon/ext/argparse/flask.py
flask_gordon/ext/argparse/gunicorn.py
flask_gordon/ext/celery/__init__.py
flask_gordon/ext/celery/celery.py
flask_gordon/ext/logger/__init__.py
flask_gordon/ext/logger/logger.py
flask_gordon/middleware/__init__.py
flask_gordon/middleware/before_first_call.py
flask_gordon/middleware/dispatcher.py
flask_gordon/testing/__init__.py
flask_gordon/testing/liveapp.py
flask_gordon/testing/playwright.py
flask_gordon-0.23.1.dist-info/LICENSE
flask_gordon-0.23.1.dist-info/METADATA
flask_gordon-0.23.1.dist-info/WHEEL
flask_gordon-0.23.1.dist-info/entry_points.txt
flask_gordon-0.23.1.dist-info/top_level.txt
flask_gordon-0.23.1.dist-info/zip-safe
flask_gordon-0.23.1.dist-info/RECORD
