Metadata-Version: 2.1
Name: flask-gordon
Version: 0.23.1
Summary: Flask, Celery, and SQLAlchemy blueprints, routes, middlewares and extensions.
Author-email: Julien Lecomte <julien@lecomte.at>
License: MIT
Project-URL: Homepage, https://gitlab.com/cappysan/python/flask-gordon
Project-URL: Documentation, https://cappysan.gitlab.io/python/flask-gordon
Project-URL: Source code, https://gitlab.com/cappysan/python/flask-gordon
Project-URL: Bug tracker, https://gitlab.com/cappysan/python/flask-gordon/-/issues
Classifier: License :: OSI Approved :: MIT License
Classifier: Intended Audience :: Developers
Classifier: Topic :: Internet :: WWW/HTTP :: HTTP Servers
Classifier: Topic :: Internet :: WWW/HTTP :: WSGI :: Application
Classifier: Topic :: Internet :: WWW/HTTP :: WSGI :: Middleware
Classifier: Topic :: Internet :: WWW/HTTP :: WSGI :: Server
Classifier: Framework :: Flask
Classifier: Development Status :: 4 - Beta
Classifier: Programming Language :: Python :: 3 :: Only
Classifier: Programming Language :: Python :: 3.8
Classifier: Programming Language :: Python :: 3.9
Classifier: Programming Language :: Python :: 3.10
Classifier: Programming Language :: Python :: 3.11
Requires-Python: >=3.8
License-File: LICENSE
Requires-Dist: flask <3.0.0
Requires-Dist: werkzeug <3.0.0
Requires-Dist: pyyaml
Requires-Dist: torxtools >=1.0.4
Provides-Extra: celery
Requires-Dist: celery[redis] ; extra == 'celery'
Provides-Extra: dev
Requires-Dist: playwright ; extra == 'dev'
Requires-Dist: pytest ; extra == 'dev'
Requires-Dist: pytest-flask ; extra == 'dev'
Requires-Dist: pytest-playwright ; extra == 'dev'
Requires-Dist: responses ; extra == 'dev'
